{"schema":"econ_params_v2","generated":"2026-06-28","method":"Per-state blended stumpage in real USD/m3, region-aware. Built from TimberMart South + state-agency saw ($/MBF) and pulp ($/cord) real-$ medians: saw/MBF -> /m3 at 4.7 (East) or 5.5 (West) m3 per MBF log scale; cord -> /m3 at 2.55. Blended by a regional sawtimber product share (West 0.80, South 0.55, North-Central 0.45, Northeast 0.45). Missing saw or pulp imputed from the regional median; states without TimberMart data use the regional mean.","conversions":{"mbf_to_m3":{"Northeast":4.7,"South":4.7,"North Central":4.7,"West":5.5},"cord_to_m3":2.55,"saw_share_by_region":{"Northeast":0.45,"South":0.55,"North Central":0.45,"West":0.8}},"stumpage_usd_m3":{"AL":44.68,"AR":45.07,"AZ":45.22,"CA":45.22,"CO":45.22,"CT":24.22,"DE":24.22,"FL":50.4,"GA":46.95,"IA":16.52,"ID":35.23,"IL":28.62,"IN":16.52,"KS":45.22,"KY":44.08,"LA":42.25,"MA":24.22,"MD":24.22,"ME":24.66,"MI":14.74,"MN":13.45,"MO":14.81,"MS":39.15,"MT":45.22,"NC":31.49,"ND":45.22,"NE":45.22,"NH":17.41,"NJ":24.22,"NM":45.22,"NV":45.22,"NY":21.26,"OH":30.51,"OK":44.08,"OR":45.22,"PA":24.22,"RI":24.22,"SC":40.27,"SD":45.22,"TN":35.35,"TX":45.07,"UT":45.22,"VA":30,"VT":16.18,"WA":45.22,"WI":9.36,"WV":33.43,"WY":45.22},"basis":{"AL":"measured","AR":"measured","AZ":"regional","CA":"regional","CO":"regional","CT":"regional","DE":"regional","FL":"measured","GA":"measured","IA":"regional","ID":"partial","IL":"partial","IN":"regional","KS":"regional","KY":"regional","LA":"measured","MA":"regional","MD":"regional","ME":"measured","MI":"measured","MN":"measured","MO":"measured","MS":"measured","MT":"regional","NC":"measured","ND":"regional","NE":"regional","NH":"partial","NJ":"regional","NM":"regional","NV":"regional","NY":"partial","OH":"partial","OK":"regional","OR":"regional","PA":"partial","RI":"regional","SC":"measured","SD":"regional","TN":"measured","TX":"measured","UT":"regional","VA":"measured","VT":"measured","WA":"partial","WI":"measured","WV":"partial","WY":"regional"},"detail":{"AL":{"saw_usd_mbf":312,"pulp_usd_cord":46.2,"saw_m3":66.4,"pulp_m3":18.1,"region":"South","saw_share":0.55,"n_min":4,"imputed":[]},"AR":{"saw_usd_mbf":334,"pulp_usd_cord":34.1,"saw_m3":71,"pulp_m3":13.4,"region":"South","saw_share":0.55,"n_min":4,"imputed":[]},"FL":{"saw_usd_mbf":340,"pulp_usd_cord":60.3,"saw_m3":72.3,"pulp_m3":23.6,"region":"South","saw_share":0.55,"n_min":4,"imputed":[]},"GA":{"saw_usd_mbf":324,"pulp_usd_cord":51.2,"saw_m3":69,"pulp_m3":20.1,"region":"South","saw_share":0.55,"n_min":4,"imputed":[]},"ID":{"saw_usd_mbf":224,"pulp_usd_cord":null,"saw_m3":40.7,"pulp_m3":13.4,"region":"West","saw_share":0.8,"n_min":62,"imputed":["pulp"]},"IL":{"saw_usd_mbf":268,"pulp_usd_cord":null,"saw_m3":57,"pulp_m3":5.4,"region":"North Central","saw_share":0.45,"n_min":61,"imputed":["pulp"]},"LA":{"saw_usd_mbf":300,"pulp_usd_cord":40.3,"saw_m3":63.9,"pulp_m3":15.8,"region":"South","saw_share":0.55,"n_min":4,"imputed":[]},"ME":{"saw_usd_mbf":202,"pulp_usd_cord":24.8,"saw_m3":42.9,"pulp_m3":9.7,"region":"Northeast","saw_share":0.45,"n_min":111,"imputed":[]},"MI":{"saw_usd_mbf":101,"pulp_usd_cord":23.6,"saw_m3":21.4,"pulp_m3":9.3,"region":"North Central","saw_share":0.45,"n_min":282,"imputed":[]},"MN":{"saw_usd_mbf":109,"pulp_usd_cord":13.9,"saw_m3":23.3,"pulp_m3":5.4,"region":"North Central","saw_share":0.45,"n_min":19,"imputed":[]},"MO":{"saw_usd_mbf":141,"pulp_usd_cord":5.9,"saw_m3":30.1,"pulp_m3":2.3,"region":"North Central","saw_share":0.45,"n_min":6,"imputed":[]},"MS":{"saw_usd_mbf":284,"pulp_usd_cord":33.8,"saw_m3":60.3,"pulp_m3":13.3,"region":"South","saw_share":0.55,"n_min":4,"imputed":[]},"NC":{"saw_usd_mbf":242,"pulp_usd_cord":18.1,"saw_m3":51.4,"pulp_m3":7.1,"region":"South","saw_share":0.55,"n_min":3,"imputed":[]},"NH":{"saw_usd_mbf":126,"pulp_usd_cord":null,"saw_m3":26.8,"pulp_m3":9.7,"region":"Northeast","saw_share":0.45,"n_min":30,"imputed":["pulp"]},"NY":{"saw_usd_mbf":null,"pulp_usd_cord":11,"saw_m3":42,"pulp_m3":4.3,"region":"Northeast","saw_share":0.45,"n_min":22,"imputed":["saw"]},"OH":{"saw_usd_mbf":288,"pulp_usd_cord":null,"saw_m3":61.2,"pulp_m3":5.4,"region":"North Central","saw_share":0.45,"n_min":6,"imputed":["pulp"]},"PA":{"saw_usd_mbf":197,"pulp_usd_cord":null,"saw_m3":42,"pulp_m3":9.7,"region":"Northeast","saw_share":0.45,"n_min":68,"imputed":["pulp"]},"SC":{"saw_usd_mbf":271,"pulp_usd_cord":48.8,"saw_m3":57.6,"pulp_m3":19.1,"region":"South","saw_share":0.55,"n_min":4,"imputed":[]},"TN":{"saw_usd_mbf":248,"pulp_usd_cord":35.6,"saw_m3":52.8,"pulp_m3":14,"region":"South","saw_share":0.55,"n_min":4,"imputed":[]},"TX":{"saw_usd_mbf":321,"pulp_usd_cord":42.8,"saw_m3":68.2,"pulp_m3":16.8,"region":"South","saw_share":0.55,"n_min":4,"imputed":[]},"VA":{"saw_usd_mbf":196,"pulp_usd_cord":52,"saw_m3":41.7,"pulp_m3":20.4,"region":"Northeast","saw_share":0.45,"n_min":3,"imputed":[]},"VT":{"saw_usd_mbf":163,"pulp_usd_cord":2.8,"saw_m3":34.6,"pulp_m3":1.1,"region":"Northeast","saw_share":0.45,"n_min":3,"imputed":[]},"WA":{"saw_usd_mbf":293,"pulp_usd_cord":null,"saw_m3":53.2,"pulp_m3":13.4,"region":"West","saw_share":0.8,"n_min":4,"imputed":["pulp"]},"WI":{"saw_usd_mbf":92,"pulp_usd_cord":2.3,"saw_m3":19.7,"pulp_m3":0.9,"region":"North Central","saw_share":0.45,"n_min":6,"imputed":[]},"WV":{"saw_usd_mbf":293,"pulp_usd_cord":null,"saw_m3":62.4,"pulp_m3":9.7,"region":"Northeast","saw_share":0.45,"n_min":50,"imputed":["pulp"]}},"regional_mean_usd_m3":{"Northeast":24.04,"South":42.4,"North Central":18.07,"West":44.55},"national_mean_usd_m3":34.05}